ElGateau/ElGateau.py
ElGateau/__init__.py
ElGateau/fonts/Hack-Bold.ttf
ElGateau/fonts/Hack-BoldItalic.ttf
ElGateau/fonts/Hack-Italic.ttf
ElGateau/fonts/Hack-Regular.ttf
ElGateau/fonts/Hack_license.txt
ElGateau/fonts/Inconsolata-Bold.ttf
ElGateau/fonts/Inconsolata-Regular.ttf
ElGateau/fonts/Inconsolata_license.txt
ElGateau/fonts/KawkabMono-Bold.ttf
ElGateau/fonts/KawkabMono-Light.ttf
ElGateau/fonts/KawkabMono-Regular.ttf
ElGateau/fonts/KawkabMono_license.txt
ElGateau/fonts/LiberationMono-Bold.ttf
ElGateau/fonts/LiberationMono-BoldItalic.ttf
ElGateau/fonts/LiberationMono-Italic.ttf
ElGateau/fonts/LiberationMono-Regular.ttf
ElGateau/fonts/LiberationMono_license.txt
ElGateau/fonts/VeraMono-Bold-Italic.ttf
ElGateau/fonts/VeraMono-Bold.ttf
ElGateau/fonts/VeraMono-Italic.ttf
ElGateau/fonts/VeraMono.ttf
ElGateau/fonts/VeraMono_license.txt
ElGateau/fonts/agave.ttf
ElGateau/fonts/agave_license.txt
ElGateau/fonts/emoji.ttf
ElGateau/fonts/emoji_license.txt
ElGateau/fonts/gohufont-uni-11.ttf
ElGateau/fonts/gohufont-uni-14.ttf
ElGateau/fonts/gohufont_license.txt
ElGateau/icons/bulb.png
ElGateau/icons/cake.png
ElGateau/icons/card.png
ElGateau/icons/cheese.png
ElGateau/icons/circle.png
ElGateau/icons/devil.png
ElGateau/icons/door.png
ElGateau/icons/fire.png
ElGateau/icons/floppy.png
ElGateau/icons/hammer.png
ElGateau/icons/heart.png
ElGateau/icons/liberty.png
ElGateau/icons/money.png
ElGateau/icons/mushroom.png
ElGateau/icons/present.png
ElGateau/icons/rat.png
ElGateau/icons/rocket.png
ElGateau/icons/square.png
ElGateau/icons/suit_club.png
ElGateau/icons/suit_diam.png
ElGateau/icons/suit_heart.png
ElGateau/icons/suit_spade.png
ElGateau/icons/taco.png
ElGateau/icons/trophy.png
ElGateau/icons/turtle.png
ElGateau-1.0.1.dist-info/LICENSE
ElGateau-1.0.1.dist-info/METADATA
ElGateau-1.0.1.dist-info/WHEEL
ElGateau-1.0.1.dist-info/top_level.txt
ElGateau-1.0.1.dist-info/RECORD
