Metadata-Version: 2.1
Name: ElGateau
Version: 1.0.1
Summary: A Library for Using the Elgato Stream Deck for Experimental Psychology Research
Home-page: https://github.com/cMadan/ElGateau
Author: Christopher Madan
Author-email: christopher.madan@nottingham.ac.uk
License: MIT
Platform: any
Classifier: Programming Language :: Python :: 3
Classifier: License :: OSI Approved :: MIT License
Classifier: Operating System :: OS Independent
Classifier: Intended Audience :: Science/Research
Requires-Dist: hidapi
Requires-Dist: Pillow
